svn2git/__init__.py
svn2git/__main__.py
svn2git/env_default_action.py
svn2git/git.py
svn2git/options.py
svn2git/svn.py
svn2git/svn_store_plaintext_password.py
svn2git/utils.py
svn2git-0.10.0.dist-info/METADATA
svn2git-0.10.0.dist-info/WHEEL
svn2git-0.10.0.dist-info/entry_points.txt
svn2git-0.10.0.dist-info/RECORD
