Metadata-Version: 2.1
Name: svn2git
Version: 0.10.0
Summary: A tool for migrating svn projects to git
Home-page: https://helmergmbh.github.io/svn2git/
License: MIT
Author: Pascal Helmer
Author-email: pascal@pascalhelmer.de
Requires-Python: >=3.11,<4.0
Classifier: License :: OSI Approved :: MIT License
Classifier: Programming Language :: Python :: 3
Classifier: Programming Language :: Python :: 3.11
Classifier: Programming Language :: Python :: 3.12
Project-URL: Repository, https://github.com/helmergmbh/svn2git
